{
	"configurations" : 
	[
		{
			"directories" : 
			[
				{
					"build" : ".",
					"jsonFile" : "directory-.-Debug-d0094a50bb2071803777.json",
					"projectIndex" : 0,
					"source" : ".",
					"targetIndexes" : 
					[
						0
					]
				}
			],
			"name" : "Debug",
			"projects" : 
			[
				{
					"directoryIndexes" : 
					[
						0
					],
					"name" : "Project",
					"targetIndexes" : 
					[
						0
					]
				}
			],
			"targets" : 
			[
				{
					"directoryIndex" : 0,
					"id" : "source_files::@6890427a1f51a3e7e1df",
					"jsonFile" : "target-source_files-Debug-8bbb42e9cfb2c48ab53b.json",
					"name" : "source_files",
					"projectIndex" : 0
				}
			]
		}
	],
	"kind" : "codemodel",
	"paths" : 
	{
		"build" : "C:/Users/rkmun/source/repos/VoxelEngine/src/build",
		"source" : "C:/Users/rkmun/source/repos/VoxelEngine/src"
	},
	"version" : 
	{
		"major" : 2,
		"minor" : 6
	}
}
